{
  "elements" : [ {
    "allowOverride" : false,
    "combinationType" : "FUNCTION",
    "displayOptions" : 0,
    "elementGroups" : [ ],
    "elementName" : "Inputs",
    "elementTimeout" : 0,
    "excludeFromExport" : false,
    "hideOnNull" : false,
    "hideWarnings" : false,
    "overridden" : false,
    "protectedExpression" : false,
    "storeInAttributeExtension" : false,
    "summarize" : false
  }, {
    "allowOverride" : false,
    "combinationType" : "FUNCTION",
    "displayOptions" : 0,
    "elementGroups" : [ ],
    "elementName" : "AbortSyntaxCheck",
    "elementTimeout" : 0,
    "excludeFromExport" : false,
    "hideOnNull" : false,
    "hideWarnings" : false,
    "overridden" : false,
    "protectedExpression" : false,
    "storeInAttributeExtension" : false,
    "summarize" : false
  }, {
    "allowOverride" : false,
    "combinationType" : "FUNCTION",
    "displayOptions" : 0,
    "elementGroups" : [ ],
    "elementName" : "BatchInfo",
    "elementTimeout" : 0,
    "excludeFromExport" : false,
    "hideOnNull" : false,
    "hideWarnings" : false,
    "overridden" : false,
    "protectedExpression" : false,
    "storeInAttributeExtension" : false,
    "summarize" : false
  }, {
    "allowOverride" : false,
    "combinationType" : "FUNCTION",
    "displayOptions" : 0,
    "elementGroups" : [ ],
    "elementName" : "IsOnlyOneRow",
    "elementTimeout" : 0,
    "excludeFromExport" : false,
    "hideOnNull" : false,
    "hideWarnings" : false,
    "overridden" : false,
    "protectedExpression" : false,
    "storeInAttributeExtension" : false,
    "summarize" : false
  }, {
    "allowOverride" : false,
    "combinationType" : "FUNCTION",
    "displayOptions" : 0,
    "elementGroups" : [ ],
    "elementName" : "Init",
    "elementTimeout" : 0,
    "excludeFromExport" : false,
    "hideOnNull" : false,
    "hideWarnings" : false,
    "overridden" : false,
    "protectedExpression" : false,
    "storeInAttributeExtension" : false,
    "summarize" : false
  }, {
    "allowOverride" : false,
    "combinationType" : "FUNCTION",
    "displayOptions" : 0,
    "elementGroups" : [ ],
    "elementName" : "LoadProducts",
    "elementTimeout" : 900,
    "excludeFromExport" : false,
    "hideOnNull" : false,
    "hideWarnings" : false,
    "overridden" : false,
    "protectedExpression" : false,
    "storeInAttributeExtension" : false,
    "summarize" : false
  }, {
    "allowOverride" : false,
    "combinationType" : "FUNCTION",
    "displayOptions" : 0,
    "elementGroups" : [ ],
    "elementName" : "LoadCurrencyConversion",
    "elementTimeout" : 0,
    "excludeFromExport" : false,
    "hideOnNull" : false,
    "hideWarnings" : false,
    "overridden" : false,
    "protectedExpression" : false,
    "storeInAttributeExtension" : false,
    "summarize" : false
  }, {
    "allowOverride" : false,
    "combinationType" : "FUNCTION",
    "displayOptions" : 0,
    "elementGroups" : [ ],
    "elementName" : "LoadCosts",
    "elementTimeout" : 900,
    "excludeFromExport" : false,
    "hideOnNull" : false,
    "hideWarnings" : false,
    "overridden" : false,
    "protectedExpression" : false,
    "storeInAttributeExtension" : false,
    "summarize" : false
  }, {
    "allowOverride" : false,
    "combinationType" : "FUNCTION",
    "displayOptions" : 0,
    "elementGroups" : [ ],
    "elementName" : "LoadConditionRecordSetMap",
    "elementTimeout" : 0,
    "excludeFromExport" : false,
    "hideOnNull" : false,
    "hideWarnings" : false,
    "overridden" : false,
    "protectedExpression" : false,
    "storeInAttributeExtension" : false,
    "summarize" : false
  }, {
    "allowOverride" : false,
    "combinationType" : "FUNCTION",
    "displayOptions" : 0,
    "elementGroups" : [ ],
    "elementName" : "GetAllNewEffectiveDates",
    "elementTimeout" : 0,
    "excludeFromExport" : false,
    "hideOnNull" : false,
    "hideWarnings" : false,
    "overridden" : false,
    "protectedExpression" : false,
    "storeInAttributeExtension" : false,
    "summarize" : false
  }, {
    "allowOverride" : false,
    "combinationType" : "FUNCTION",
    "displayOptions" : 0,
    "elementGroups" : [ ],
    "elementName" : "LoadZLIS",
    "elementTimeout" : 900,
    "excludeFromExport" : false,
    "hideOnNull" : false,
    "hideWarnings" : false,
    "overridden" : false,
    "protectedExpression" : false,
    "storeInAttributeExtension" : false,
    "summarize" : false
  }, {
    "allowOverride" : false,
    "combinationType" : "FUNCTION",
    "displayOptions" : 0,
    "elementGroups" : [ ],
    "elementName" : "LoadZLISCR",
    "elementTimeout" : 900,
    "excludeFromExport" : false,
    "hideOnNull" : false,
    "hideWarnings" : false,
    "overridden" : false,
    "protectedExpression" : false,
    "storeInAttributeExtension" : false,
    "summarize" : false
  }, {
    "allowOverride" : false,
    "combinationType" : "FUNCTION",
    "displayOptions" : 0,
    "elementGroups" : [ ],
    "elementName" : "ZLISMerged",
    "elementTimeout" : 0,
    "excludeFromExport" : false,
    "hideOnNull" : false,
    "hideWarnings" : false,
    "overridden" : false,
    "protectedExpression" : false,
    "storeInAttributeExtension" : false,
    "summarize" : false
  }, {
    "allowOverride" : false,
    "combinationType" : "FUNCTION",
    "displayOptions" : 0,
    "elementGroups" : [ ],
    "elementName" : "LoadZBPL",
    "elementTimeout" : 900,
    "excludeFromExport" : false,
    "hideOnNull" : false,
    "hideWarnings" : false,
    "overridden" : false,
    "protectedExpression" : false,
    "storeInAttributeExtension" : false,
    "summarize" : false
  }, {
    "allowOverride" : false,
    "combinationType" : "FUNCTION",
    "displayOptions" : 0,
    "elementGroups" : [ ],
    "elementName" : "LoadZBPLCR",
    "elementTimeout" : 900,
    "excludeFromExport" : false,
    "hideOnNull" : false,
    "hideWarnings" : false,
    "overridden" : false,
    "protectedExpression" : false,
    "storeInAttributeExtension" : false,
    "summarize" : false
  }, {
    "allowOverride" : false,
    "combinationType" : "FUNCTION",
    "displayOptions" : 0,
    "elementGroups" : [ ],
    "elementName" : "LoadZBPLScales",
    "elementTimeout" : 900,
    "excludeFromExport" : false,
    "hideOnNull" : false,
    "hideWarnings" : false,
    "overridden" : false,
    "protectedExpression" : false,
    "storeInAttributeExtension" : false,
    "summarize" : false
  }, {
    "allowOverride" : false,
    "combinationType" : "FUNCTION",
    "displayOptions" : 0,
    "elementGroups" : [ ],
    "elementName" : "LoadZBPLScalesCR",
    "elementTimeout" : 0,
    "excludeFromExport" : false,
    "hideOnNull" : false,
    "hideWarnings" : false,
    "overridden" : false,
    "protectedExpression" : false,
    "storeInAttributeExtension" : false,
    "summarize" : false
  }, {
    "allowOverride" : false,
    "combinationType" : "FUNCTION",
    "displayOptions" : 0,
    "elementGroups" : [ ],
    "elementName" : "ZBPLMerged",
    "elementTimeout" : 0,
    "excludeFromExport" : false,
    "hideOnNull" : false,
    "hideWarnings" : false,
    "overridden" : false,
    "protectedExpression" : false,
    "storeInAttributeExtension" : false,
    "summarize" : false
  }, {
    "allowOverride" : false,
    "combinationType" : "FUNCTION",
    "displayOptions" : 0,
    "elementGroups" : [ ],
    "elementName" : "LoadPricelists",
    "elementTimeout" : 900,
    "excludeFromExport" : false,
    "hideOnNull" : false,
    "hideWarnings" : false,
    "overridden" : false,
    "protectedExpression" : false,
    "storeInAttributeExtension" : false,
    "summarize" : false
  }, {
    "allowOverride" : false,
    "combinationType" : "FUNCTION",
    "displayOptions" : 0,
    "elementGroups" : [ ],
    "elementName" : "LoadGlobalUOMConversion",
    "elementTimeout" : 0,
    "excludeFromExport" : false,
    "hideOnNull" : false,
    "hideWarnings" : false,
    "overridden" : false,
    "protectedExpression" : false,
    "storeInAttributeExtension" : false,
    "summarize" : false
  }, {
    "allowOverride" : false,
    "combinationType" : "FUNCTION",
    "displayOptions" : 0,
    "elementGroups" : [ ],
    "elementName" : "LoadUOMConversion",
    "elementTimeout" : 0,
    "excludeFromExport" : false,
    "hideOnNull" : false,
    "hideWarnings" : false,
    "overridden" : false,
    "protectedExpression" : false,
    "storeInAttributeExtension" : false,
    "summarize" : false
  }, {
    "allowOverride" : false,
    "combinationType" : "FUNCTION",
    "displayOptions" : 0,
    "elementGroups" : [ ],
    "elementName" : "LoadUOMOptions",
    "elementTimeout" : 0,
    "excludeFromExport" : false,
    "hideOnNull" : false,
    "hideWarnings" : false,
    "overridden" : false,
    "protectedExpression" : false,
    "storeInAttributeExtension" : false,
    "summarize" : false
  }, {
    "allowOverride" : false,
    "combinationType" : "FUNCTION",
    "displayOptions" : 0,
    "elementGroups" : [ ],
    "elementName" : "LoadOverridablePricelistItems",
    "elementTimeout" : 0,
    "excludeFromExport" : false,
    "hideOnNull" : false,
    "hideWarnings" : false,
    "overridden" : false,
    "protectedExpression" : false,
    "storeInAttributeExtension" : false,
    "summarize" : false
  }, {
    "allowOverride" : false,
    "combinationType" : "FUNCTION",
    "displayOptions" : 0,
    "elementGroups" : [ ],
    "elementName" : "ManualOverrides",
    "elementTimeout" : 0,
    "excludeFromExport" : false,
    "hideOnNull" : false,
    "hideWarnings" : false,
    "overridden" : false,
    "protectedExpression" : false,
    "storeInAttributeExtension" : false,
    "summarize" : false
  }, {
    "allowOverride" : false,
    "combinationType" : "FUNCTION",
    "displayOptions" : 0,
    "elementGroups" : [ ],
    "elementName" : "IsPriceChangePerUOM",
    "elementTimeout" : 0,
    "excludeFromExport" : false,
    "hideOnNull" : false,
    "hideWarnings" : false,
    "overridden" : false,
    "protectedExpression" : false,
    "storeInAttributeExtension" : false,
    "summarize" : false
  }, {
    "allowOverride" : false,
    "combinationType" : "FUNCTION",
    "displayOptions" : 0,
    "elementGroups" : [ ],
    "elementName" : "IsPriceChangePercent",
    "elementTimeout" : 0,
    "excludeFromExport" : false,
    "hideOnNull" : false,
    "hideWarnings" : false,
    "overridden" : false,
    "protectedExpression" : false,
    "storeInAttributeExtension" : false,
    "summarize" : false
  }, {
    "allowOverride" : false,
    "combinationType" : "FUNCTION",
    "displayOptions" : 0,
    "elementGroups" : [ ],
    "elementName" : "IsPLSelected",
    "elementTimeout" : 0,
    "excludeFromExport" : false,
    "hideOnNull" : false,
    "hideWarnings" : false,
    "overridden" : false,
    "protectedExpression" : false,
    "storeInAttributeExtension" : false,
    "summarize" : false
  }, {
    "allowOverride" : false,
    "combinationType" : "FUNCTION",
    "displayOptions" : 1,
    "elementGroups" : [ ],
    "elementLabel" : "Sales Org",
    "elementName" : "SalesOrg",
    "elementTimeout" : 0,
    "excludeFromExport" : false,
    "formatType" : "TEXT",
    "hideOnNull" : false,
    "hideWarnings" : false,
    "overridden" : false,
    "protectedExpression" : false,
    "storeInAttributeExtension" : false,
    "summarize" : false
  }, {
    "allowOverride" : false,
    "combinationType" : "FUNCTION",
    "displayOptions" : 1,
    "elementGroups" : [ ],
    "elementLabel" : "Distribution Channel",
    "elementName" : "DistributionChannel",
    "elementTimeout" : 0,
    "excludeFromExport" : false,
    "formatType" : "TEXT",
    "hideOnNull" : false,
    "hideWarnings" : false,
    "overridden" : false,
    "protectedExpression" : false,
    "storeInAttributeExtension" : false,
    "summarize" : false
  }, {
    "allowOverride" : false,
    "combinationType" : "FUNCTION",
    "displayOptions" : 1,
    "elementGroups" : [ ],
    "elementLabel" : "Pricelist Number",
    "elementName" : "PricelistNumber",
    "elementTimeout" : 0,
    "excludeFromExport" : false,
    "formatType" : "TEXT",
    "hideOnNull" : false,
    "hideWarnings" : false,
    "overridden" : false,
    "protectedExpression" : false,
    "storeInAttributeExtension" : false,
    "summarize" : false
  }, {
    "allowOverride" : false,
    "combinationType" : "FUNCTION",
    "displayOptions" : 1,
    "elementGroups" : [ ],
    "elementLabel" : "Pricelist Name",
    "elementName" : "Pricelist",
    "elementTimeout" : 0,
    "excludeFromExport" : false,
    "formatType" : "TEXT",
    "hideOnNull" : false,
    "hideWarnings" : false,
    "overridden" : false,
    "protectedExpression" : false,
    "storeInAttributeExtension" : false,
    "summarize" : false
  }, {
    "allowOverride" : false,
    "combinationType" : "FUNCTION",
    "displayOptions" : 1,
    "elementGroups" : [ ],
    "elementLabel" : "Per",
    "elementName" : "Per",
    "elementTimeout" : 0,
    "excludeFromExport" : false,
    "formatType" : "NUMERIC",
    "hideOnNull" : false,
    "hideWarnings" : false,
    "overridden" : false,
    "protectedExpression" : false,
    "storeInAttributeExtension" : false,
    "summarize" : false
  }, {
    "allowOverride" : false,
    "combinationType" : "FUNCTION",
    "displayOptions" : 1,
    "elementGroups" : [ ],
    "elementLabel" : "Currency",
    "elementName" : "Currency",
    "elementTimeout" : 0,
    "excludeFromExport" : false,
    "formatType" : "TEXT",
    "hideOnNull" : false,
    "hideWarnings" : false,
    "overridden" : false,
    "protectedExpression" : false,
    "storeInAttributeExtension" : false,
    "summarize" : false
  }, {
    "allowOverride" : false,
    "combinationType" : "FUNCTION",
    "displayOptions" : 1,
    "elementGroups" : [ ],
    "elementLabel" : "Product Hierarchy",
    "elementName" : "ProductHierarchy",
    "elementTimeout" : 0,
    "excludeFromExport" : false,
    "formatType" : "TEXT",
    "hideOnNull" : false,
    "hideWarnings" : false,
    "overridden" : false,
    "protectedExpression" : false,
    "storeInAttributeExtension" : false,
    "summarize" : false
  }, {
    "allowOverride" : false,
    "combinationType" : "FUNCTION",
    "displayOptions" : 1,
    "elementGroups" : [ ],
    "elementLabel" : "Previous List Price (ZLIS)",
    "elementName" : "CurrentListPrice",
    "elementTimeout" : 0,
    "excludeFromExport" : false,
    "formatType" : "MONEY",
    "hideOnNull" : false,
    "hideWarnings" : false,
    "overridden" : false,
    "protectedExpression" : false,
    "storeInAttributeExtension" : false,
    "summarize" : false
  }, {
    "allowOverride" : true,
    "combinationType" : "FUNCTION",
    "displayOptions" : 1,
    "elementGroups" : [ ],
    "elementLabel" : "ZLIS UOM",
    "elementName" : "PriceUOM",
    "elementTimeout" : 0,
    "excludeFromExport" : false,
    "formatType" : "TEXT",
    "hideOnNull" : false,
    "hideWarnings" : false,
    "overridden" : false,
    "protectedExpression" : false,
    "storeInAttributeExtension" : false,
    "summarize" : false
  }, {
    "allowOverride" : false,
    "combinationType" : "FUNCTION",
    "conditionElementName" : "IsPLSelected",
    "displayOptions" : 1,
    "elementGroups" : [ ],
    "elementLabel" : "Previous Base Price (ZBPL)",
    "elementName" : "CurrentBasePrice",
    "elementTimeout" : 0,
    "excludeFromExport" : false,
    "formatType" : "MONEY",
    "hideOnNull" : false,
    "hideWarnings" : false,
    "overridden" : false,
    "protectedExpression" : false,
    "storeInAttributeExtension" : false,
    "summarize" : false
  }, {
    "allowOverride" : false,
    "combinationType" : "FUNCTION",
    "conditionElementName" : "IsPLSelected",
    "displayOptions" : 1,
    "elementGroups" : [ ],
    "elementLabel" : "ZBPL UOM",
    "elementName" : "BaseUOM",
    "elementTimeout" : 0,
    "excludeFromExport" : false,
    "formatType" : "TEXT",
    "hideOnNull" : false,
    "hideWarnings" : false,
    "overridden" : false,
    "protectedExpression" : false,
    "storeInAttributeExtension" : false,
    "summarize" : false
  }, {
    "allowOverride" : true,
    "combinationType" : "FUNCTION",
    "conditionElementName" : "IsPLSelected",
    "displayOptions" : 1,
    "elementGroups" : [ ],
    "elementLabel" : "Scale Qty",
    "elementName" : "ScaleQty",
    "elementTimeout" : 0,
    "excludeFromExport" : false,
    "formatType" : "INTEGER",
    "hideOnNull" : false,
    "hideWarnings" : false,
    "overridden" : false,
    "protectedExpression" : false,
    "storeInAttributeExtension" : false,
    "summarize" : false
  }, {
    "allowOverride" : true,
    "combinationType" : "FUNCTION",
    "conditionElementName" : "IsPLSelected",
    "displayOptions" : 1,
    "elementGroups" : [ ],
    "elementLabel" : "Scale Qty UOM",
    "elementName" : "ScaleQtyUOM",
    "elementTimeout" : 0,
    "excludeFromExport" : false,
    "formatType" : "TEXT",
    "hideOnNull" : false,
    "hideWarnings" : false,
    "overridden" : false,
    "protectedExpression" : false,
    "storeInAttributeExtension" : false,
    "summarize" : false
  }, {
    "allowOverride" : false,
    "combinationType" : "FUNCTION",
    "displayOptions" : 1,
    "elementGroups" : [ ],
    "elementLabel" : "Previous Effective Date",
    "elementName" : "CurrentEffectiveDate",
    "elementTimeout" : 0,
    "excludeFromExport" : false,
    "formatType" : "DATE",
    "hideOnNull" : false,
    "hideWarnings" : false,
    "overridden" : false,
    "protectedExpression" : false,
    "storeInAttributeExtension" : false,
    "summarize" : false
  }, {
    "allowOverride" : false,
    "combinationType" : "FUNCTION",
    "displayOptions" : 1,
    "elementGroups" : [ ],
    "elementLabel" : "Previous Expiration Date (From ZLIS)",
    "elementName" : "CurrentExpirationDate",
    "elementTimeout" : 0,
    "excludeFromExport" : false,
    "formatType" : "DATE",
    "hideOnNull" : false,
    "hideWarnings" : false,
    "overridden" : false,
    "protectedExpression" : false,
    "storeInAttributeExtension" : false,
    "summarize" : false
  }, {
    "allowOverride" : true,
    "combinationType" : "FUNCTION",
    "displayOptions" : 1,
    "elementGroups" : [ ],
    "elementLabel" : "New Effective Date",
    "elementName" : "NewEffectiveDate",
    "elementTimeout" : 0,
    "excludeFromExport" : false,
    "formatType" : "DATE",
    "hideOnNull" : false,
    "hideWarnings" : false,
    "overridden" : false,
    "protectedExpression" : false,
    "storeInAttributeExtension" : false,
    "summarize" : false
  }, {
    "allowOverride" : true,
    "combinationType" : "FUNCTION",
    "displayOptions" : 1,
    "elementGroups" : [ ],
    "elementLabel" : "New Expiration Date",
    "elementName" : "NewExpirationDate",
    "elementTimeout" : 0,
    "excludeFromExport" : false,
    "formatType" : "DATE",
    "hideOnNull" : false,
    "hideWarnings" : false,
    "overridden" : false,
    "protectedExpression" : false,
    "storeInAttributeExtension" : false,
    "summarize" : false
  }, {
    "allowOverride" : true,
    "combinationType" : "FUNCTION",
    "conditionElementName" : "IsPriceChangePerUOM",
    "displayOptions" : 1,
    "elementGroups" : [ ],
    "elementLabel" : "List Price Change $ per UOM",
    "elementName" : "ListPriceChangePerUOM",
    "elementTimeout" : 0,
    "excludeFromExport" : false,
    "formatType" : "MONEY",
    "hideOnNull" : false,
    "hideWarnings" : false,
    "overridden" : false,
    "protectedExpression" : false,
    "storeInAttributeExtension" : false,
    "summarize" : false
  }, {
    "allowOverride" : true,
    "combinationType" : "FUNCTION",
    "conditionElementName" : "IsPriceChangePerUOM",
    "displayOptions" : 1,
    "elementGroups" : [ ],
    "elementLabel" : "List Price Change UOM",
    "elementName" : "ListPriceChangeUOM",
    "elementTimeout" : 0,
    "excludeFromExport" : false,
    "formatType" : "TEXT",
    "hideOnNull" : false,
    "hideWarnings" : false,
    "overridden" : false,
    "protectedExpression" : false,
    "storeInAttributeExtension" : false,
    "summarize" : false
  }, {
    "allowOverride" : true,
    "combinationType" : "FUNCTION",
    "conditionElementName" : "IsPriceChangePerUOM",
    "displayOptions" : 1,
    "elementGroups" : [ ],
    "elementLabel" : "Base Price Change $ per UOM",
    "elementName" : "BasePriceChangePerUOM",
    "elementTimeout" : 0,
    "excludeFromExport" : false,
    "formatType" : "MONEY",
    "hideOnNull" : false,
    "hideWarnings" : false,
    "overridden" : false,
    "protectedExpression" : false,
    "storeInAttributeExtension" : false,
    "summarize" : false
  }, {
    "allowOverride" : true,
    "combinationType" : "FUNCTION",
    "conditionElementName" : "IsPriceChangePerUOM",
    "displayOptions" : 1,
    "elementGroups" : [ ],
    "elementLabel" : "Base Price Change UOM",
    "elementName" : "BasePriceChangeUOM",
    "elementTimeout" : 0,
    "excludeFromExport" : false,
    "formatType" : "TEXT",
    "hideOnNull" : false,
    "hideWarnings" : false,
    "overridden" : false,
    "protectedExpression" : false,
    "storeInAttributeExtension" : false,
    "summarize" : false
  }, {
    "allowOverride" : true,
    "combinationType" : "FUNCTION",
    "conditionElementName" : "IsPriceChangePercent",
    "displayOptions" : 1,
    "elementGroups" : [ ],
    "elementLabel" : "List Price Change %",
    "elementName" : "ListPriceChangePercent",
    "elementTimeout" : 0,
    "excludeFromExport" : false,
    "formatType" : "PERCENT",
    "hideOnNull" : false,
    "hideWarnings" : false,
    "overridden" : false,
    "protectedExpression" : false,
    "storeInAttributeExtension" : false,
    "summarize" : false
  }, {
    "allowOverride" : true,
    "combinationType" : "FUNCTION",
    "conditionElementName" : "IsPriceChangePercent",
    "displayOptions" : 1,
    "elementGroups" : [ ],
    "elementLabel" : "Base Price Change %",
    "elementName" : "BasePriceChangePercent",
    "elementTimeout" : 0,
    "excludeFromExport" : false,
    "formatType" : "PERCENT",
    "hideOnNull" : false,
    "hideWarnings" : false,
    "overridden" : false,
    "protectedExpression" : false,
    "storeInAttributeExtension" : false,
    "summarize" : false
  }, {
    "allowOverride" : false,
    "combinationType" : "FUNCTION",
    "displayOptions" : 0,
    "elementGroups" : [ ],
    "elementName" : "NewListPriceValue",
    "elementTimeout" : 0,
    "excludeFromExport" : false,
    "formatType" : "MONEY",
    "hideOnNull" : false,
    "hideWarnings" : false,
    "overridden" : false,
    "protectedExpression" : false,
    "storeInAttributeExtension" : false,
    "summarize" : false
  }, {
    "allowOverride" : false,
    "combinationType" : "FUNCTION",
    "displayOptions" : 1,
    "elementGroups" : [ ],
    "elementLabel" : "NewListPriceModifiedDatetime",
    "elementName" : "NewListPriceModifiedDatetime",
    "elementTimeout" : 0,
    "excludeFromExport" : false,
    "formatType" : "DATETIME",
    "hideOnNull" : false,
    "hideWarnings" : false,
    "overridden" : false,
    "protectedExpression" : false,
    "storeInAttributeExtension" : false,
    "summarize" : false
  }, {
    "allowOverride" : true,
    "combinationType" : "FUNCTION",
    "displayOptions" : 1,
    "elementGroups" : [ ],
    "elementLabel" : "New List Price (ZLIS)",
    "elementName" : "NewListPrice",
    "elementTimeout" : 0,
    "excludeFromExport" : false,
    "formatType" : "MONEY",
    "hideOnNull" : false,
    "hideWarnings" : false,
    "overridden" : false,
    "protectedExpression" : false,
    "storeInAttributeExtension" : false,
    "summarize" : false
  }, {
    "allowOverride" : true,
    "combinationType" : "FUNCTION",
    "displayOptions" : 1,
    "elementGroups" : [ ],
    "elementLabel" : "New Base Price (ZBPL)",
    "elementName" : "NewBasePrice",
    "elementTimeout" : 0,
    "excludeFromExport" : false,
    "formatType" : "MONEY",
    "hideOnNull" : false,
    "hideWarnings" : false,
    "overridden" : false,
    "protectedExpression" : false,
    "storeInAttributeExtension" : false,
    "summarize" : false
  }, {
    "allowOverride" : false,
    "combinationType" : "FUNCTION",
    "displayOptions" : 1,
    "elementGroups" : [ ],
    "elementLabel" : "List Price Change $",
    "elementName" : "ListPriceChange",
    "elementTimeout" : 0,
    "excludeFromExport" : false,
    "formatType" : "MONEY",
    "hideOnNull" : false,
    "hideWarnings" : false,
    "overridden" : false,
    "protectedExpression" : false,
    "storeInAttributeExtension" : false,
    "summarize" : false
  }, {
    "allowOverride" : false,
    "combinationType" : "FUNCTION",
    "displayOptions" : 1,
    "elementGroups" : [ ],
    "elementLabel" : "Base Price Change $",
    "elementName" : "BasePriceChange",
    "elementTimeout" : 0,
    "excludeFromExport" : false,
    "formatType" : "MONEY",
    "hideOnNull" : false,
    "hideWarnings" : false,
    "overridden" : false,
    "protectedExpression" : false,
    "storeInAttributeExtension" : false,
    "summarize" : false
  }, {
    "allowOverride" : false,
    "combinationType" : "FUNCTION",
    "displayOptions" : 1,
    "elementGroups" : [ ],
    "elementLabel" : "Cost",
    "elementName" : "Cost",
    "elementTimeout" : 0,
    "excludeFromExport" : false,
    "formatType" : "MONEY",
    "hideOnNull" : false,
    "hideWarnings" : false,
    "overridden" : false,
    "protectedExpression" : false,
    "storeInAttributeExtension" : false,
    "summarize" : false
  }, {
    "allowOverride" : false,
    "combinationType" : "FUNCTION",
    "displayOptions" : 1,
    "elementGroups" : [ ],
    "elementLabel" : "Margin %",
    "elementName" : "MarginPercent",
    "elementTimeout" : 0,
    "excludeFromExport" : false,
    "formatType" : "PERCENT",
    "hideOnNull" : false,
    "hideWarnings" : false,
    "overridden" : false,
    "protectedExpression" : false,
    "storeInAttributeExtension" : false,
    "summarize" : false
  }, {
    "allowOverride" : false,
    "combinationType" : "FUNCTION",
    "displayOptions" : 0,
    "elementGroups" : [ ],
    "elementName" : "LoadBasePricings",
    "elementTimeout" : 900,
    "excludeFromExport" : false,
    "hideOnNull" : false,
    "hideWarnings" : false,
    "overridden" : false,
    "protectedExpression" : false,
    "storeInAttributeExtension" : false,
    "summarize" : false
  }, {
    "allowOverride" : false,
    "combinationType" : "FUNCTION",
    "displayOptions" : 0,
    "elementGroups" : [ ],
    "elementName" : "CalculateJobberDealerPercent",
    "elementTimeout" : 0,
    "excludeFromExport" : false,
    "hideOnNull" : false,
    "hideWarnings" : false,
    "overridden" : false,
    "protectedExpression" : false,
    "storeInAttributeExtension" : false,
    "summarize" : false
  }, {
    "allowOverride" : false,
    "combinationType" : "FUNCTION",
    "displayOptions" : 1,
    "elementGroups" : [ ],
    "elementLabel" : "JobberDealerModifiedDatetime",
    "elementName" : "JobberDealerModifiedDatetime",
    "elementTimeout" : 0,
    "excludeFromExport" : false,
    "formatType" : "DATETIME",
    "hideOnNull" : false,
    "hideWarnings" : false,
    "overridden" : false,
    "protectedExpression" : false,
    "storeInAttributeExtension" : false,
    "summarize" : false
  }, {
    "allowOverride" : true,
    "combinationType" : "FUNCTION",
    "displayOptions" : 1,
    "elementGroups" : [ ],
    "elementLabel" : "Jobber / Dealer %",
    "elementName" : "JobberDealerPercent",
    "elementTimeout" : 0,
    "excludeFromExport" : false,
    "formatType" : "PERCENT",
    "hideOnNull" : false,
    "hideWarnings" : false,
    "overridden" : false,
    "protectedExpression" : false,
    "storeInAttributeExtension" : false,
    "summarize" : false
  }, {
    "allowOverride" : true,
    "combinationType" : "FUNCTION",
    "displayOptions" : 1,
    "elementGroups" : [ ],
    "elementLabel" : "New Jobber / Dealer Price (Each)",
    "elementName" : "NewJobberDealerPrice",
    "elementTimeout" : 0,
    "excludeFromExport" : false,
    "formatType" : "MONEY",
    "hideOnNull" : false,
    "hideWarnings" : false,
    "overridden" : false,
    "protectedExpression" : false,
    "storeInAttributeExtension" : false,
    "summarize" : false
  }, {
    "allowOverride" : false,
    "combinationType" : "FUNCTION",
    "displayOptions" : 0,
    "elementGroups" : [ ],
    "elementName" : "CalculateSRPPercent",
    "elementTimeout" : 0,
    "excludeFromExport" : false,
    "hideOnNull" : false,
    "hideWarnings" : false,
    "overridden" : false,
    "protectedExpression" : false,
    "storeInAttributeExtension" : false,
    "summarize" : false
  }, {
    "allowOverride" : false,
    "combinationType" : "FUNCTION",
    "displayOptions" : 1,
    "elementGroups" : [ ],
    "elementLabel" : "SRPModifiedDatetime",
    "elementName" : "SRPModifiedDatetime",
    "elementTimeout" : 0,
    "excludeFromExport" : false,
    "formatType" : "DATETIME",
    "hideOnNull" : false,
    "hideWarnings" : false,
    "overridden" : false,
    "protectedExpression" : false,
    "storeInAttributeExtension" : false,
    "summarize" : false
  }, {
    "allowOverride" : true,
    "combinationType" : "FUNCTION",
    "displayOptions" : 1,
    "elementGroups" : [ ],
    "elementLabel" : "SRP %",
    "elementName" : "SRPPercent",
    "elementTimeout" : 0,
    "excludeFromExport" : false,
    "formatType" : "PERCENT",
    "hideOnNull" : false,
    "hideWarnings" : false,
    "overridden" : false,
    "protectedExpression" : false,
    "storeInAttributeExtension" : false,
    "summarize" : false
  }, {
    "allowOverride" : true,
    "combinationType" : "FUNCTION",
    "displayOptions" : 1,
    "elementGroups" : [ ],
    "elementLabel" : "New SRP (Each)",
    "elementName" : "NewSRP",
    "elementTimeout" : 0,
    "excludeFromExport" : false,
    "formatType" : "MONEY",
    "hideOnNull" : false,
    "hideWarnings" : false,
    "overridden" : false,
    "protectedExpression" : false,
    "storeInAttributeExtension" : false,
    "summarize" : false
  }, {
    "allowOverride" : false,
    "combinationType" : "FUNCTION",
    "displayOptions" : 0,
    "elementGroups" : [ ],
    "elementName" : "CalculateMAPPercent",
    "elementTimeout" : 0,
    "excludeFromExport" : false,
    "hideOnNull" : false,
    "hideWarnings" : false,
    "overridden" : false,
    "protectedExpression" : false,
    "storeInAttributeExtension" : false,
    "summarize" : false
  }, {
    "allowOverride" : false,
    "combinationType" : "FUNCTION",
    "displayOptions" : 1,
    "elementGroups" : [ ],
    "elementLabel" : "MAPModifiedDatetime",
    "elementName" : "MAPModifiedDatetime",
    "elementTimeout" : 0,
    "excludeFromExport" : false,
    "formatType" : "DATETIME",
    "hideOnNull" : false,
    "hideWarnings" : false,
    "overridden" : false,
    "protectedExpression" : false,
    "storeInAttributeExtension" : false,
    "summarize" : false
  }, {
    "allowOverride" : true,
    "combinationType" : "FUNCTION",
    "displayOptions" : 1,
    "elementGroups" : [ ],
    "elementLabel" : "MAP %",
    "elementName" : "MAPPercent",
    "elementTimeout" : 0,
    "excludeFromExport" : false,
    "formatType" : "PERCENT",
    "hideOnNull" : false,
    "hideWarnings" : false,
    "overridden" : false,
    "protectedExpression" : false,
    "storeInAttributeExtension" : false,
    "summarize" : false
  }, {
    "allowOverride" : true,
    "combinationType" : "FUNCTION",
    "displayOptions" : 1,
    "elementGroups" : [ ],
    "elementLabel" : "New MAP Price (Each)",
    "elementName" : "NewMapPrice",
    "elementTimeout" : 0,
    "excludeFromExport" : false,
    "formatType" : "MONEY",
    "hideOnNull" : false,
    "hideWarnings" : false,
    "overridden" : false,
    "protectedExpression" : false,
    "storeInAttributeExtension" : false,
    "summarize" : false
  }, {
    "allowOverride" : false,
    "combinationType" : "FUNCTION",
    "displayOptions" : 1,
    "elementGroups" : [ ],
    "elementLabel" : "Errors",
    "elementName" : "Errors",
    "elementTimeout" : 0,
    "excludeFromExport" : false,
    "hideOnNull" : false,
    "hideWarnings" : false,
    "overridden" : false,
    "protectedExpression" : false,
    "storeInAttributeExtension" : false,
    "summarize" : false
  } ],
  "inputDescriptors" : [ ],
  "label" : "List Price Maintenance Line Item",
  "status" : "ACTIVE",
  "uniqueName" : "ListPriceMaintenanceLineItem",
  "validAfter" : "2024-01-01"
}